niwrap_greedy/greedy/__init__.py
niwrap_greedy/greedy/greedy.py
niwrap_greedy-0.8.3.dist-info/WHEEL
niwrap_greedy-0.8.3.dist-info/METADATA
niwrap_greedy-0.8.3.dist-info/RECORD
